odoo/addons/sale_loyalty_exclude/README.rst
odoo/addons/sale_loyalty_exclude/__init__.py
odoo/addons/sale_loyalty_exclude/__manifest__.py
odoo/addons/sale_loyalty_exclude/i18n/es.po
odoo/addons/sale_loyalty_exclude/i18n/fr.po
odoo/addons/sale_loyalty_exclude/i18n/it.po
odoo/addons/sale_loyalty_exclude/i18n/sale_loyalty_exclude.pot
odoo/addons/sale_loyalty_exclude/models/__init__.py
odoo/addons/sale_loyalty_exclude/models/loyalty_reward.py
odoo/addons/sale_loyalty_exclude/models/product_template.py
odoo/addons/sale_loyalty_exclude/models/sale_order.py
odoo/addons/sale_loyalty_exclude/readme/CONTRIBUTORS.rst
odoo/addons/sale_loyalty_exclude/readme/DESCRIPTION.rst
odoo/addons/sale_loyalty_exclude/readme/USAGE.rst
odoo/addons/sale_loyalty_exclude/static/description/icon.png
odoo/addons/sale_loyalty_exclude/static/description/index.html
odoo/addons/sale_loyalty_exclude/tests/__init__.py
odoo/addons/sale_loyalty_exclude/tests/test_sale_loyalty_exclude.py
odoo/addons/sale_loyalty_exclude/views/product_views.xml
odoo_addon_sale_loyalty_exclude-16.0.1.1.0.4.dist-info/METADATA
odoo_addon_sale_loyalty_exclude-16.0.1.1.0.4.dist-info/WHEEL
odoo_addon_sale_loyalty_exclude-16.0.1.1.0.4.dist-info/top_level.txt
odoo_addon_sale_loyalty_exclude-16.0.1.1.0.4.dist-info/RECORD
